{
  "version": 1,
  "created_at": "2026-06-01",
  "model_family": "monthly-hourly climate-normal residual MLP",
  "input_features": 66,
  "outputs": [
    "ghi_mean_w_m2",
    "dni_mean_w_m2",
    "dhi_mean_w_m2",
    "temp_mean_c",
    "wind_mean_m_s",
    "ghi_std_w_m2",
    "dni_std_w_m2",
    "dhi_std_w_m2",
    "temp_std_c",
    "wind_std_m_s"
  ],
  "sources": [
    {
      "source_id": "nasa_power",
      "label": "NASA POWER",
      "active": true,
      "coverage_rule": "global",
      "checkpoint_path": "rtx.homelab:~/pv-estimator-gpu/results/full_climate_normals_compressor_holdout_768x8/best_model.pt",
      "training_locations": 7056,
      "training_rows": 309391488,
      "best_epoch": 77,
      "best_validation_mae_mean": 5.101154327392578,
      "parameters": 9522442
    },
    {
      "source_id": "pvgis_era5",
      "label": "PVGIS-ERA5",
      "active": true,
      "coverage_rule": "global_land_pvgis_gateway",
      "checkpoint_path": "rtx.homelab:~/pv-estimator-gpu/results/pvgis_era5_climate_normals_compressor_768x8/best_model.pt",
      "training_locations": 1972,
      "training_rows": 328408996,
      "best_epoch": 75,
      "best_validation_mae_mean": 8.333486728010506,
      "parameters": 9522442
    },
    {
      "source_id": "pvgis_sarah3",
      "label": "PVGIS-SARAH3",
      "active": true,
      "coverage_rule": "empirical_grid_mask",
      "coverage_mask": "experiments/ml-weather/config/source_coverage/pvgis_sarah3_empirical_grid_mask.json",
      "checkpoint_path": "rtx.homelab:~/pv-estimator-gpu/results/pvgis_sarah3_climate_normals_compressor_768x8/best_model.pt",
      "training_locations": 787,
      "training_rows": 131063835,
      "best_epoch": 80,
      "best_validation_mae_mean": 7.889469525492784,
      "parameters": 9522442
    }
  ],
  "validation": {
    "benchmark_30": "experiments/ml-weather/results/2026-06-01_source_ensemble_validation.md",
    "pvgis_era5_reference_energy_mae_pct": 3.47,
    "pvgis_sarah3_reference_energy_mae_pct": 3.97,
    "mean_source_disagreement_spread_pct": 7.11
  }
}
